{
  "openapi": "3.0.0",
  "paths": {
    "/api/v1/users": {
      "post": {
        "operationId": "UsersController_createUser",
        "parameters": [],
        "requestBody": {
          "required": true,
          "content": {
            "application/json": {
              "schema": {
                "$ref": "#/components/schemas/CreateUserDto"
              }
            }
          }
        },
        "responses": {
          "201": {
            "description": "User created",
            "content": {
              "application/json": {
                "schema": {
                  "type": "object"
                }
              }
            }
          }
        },
        "summary": "Create User",
        "tags": [
          "User"
        ]
      },
      "get": {
        "operationId": "UsersController_getUsers",
        "parameters": [],
        "responses": {
          "200": {
            "description": "All users",
            "content": {
              "application/json": {
                "schema": {
                  "type": "array"
                }
              }
            }
          }
        },
        "summary": "Get Users",
        "tags": [
          "User"
        ]
      }
    }
  },
  "info": {
    "title": "TypeScript NestJS Template",
    "description": "",
    "version": "0.1.0",
    "contact": {}
  },
  "tags": [],
  "servers": [
    {
      "url": "http://localhost:3000"
    }
  ],
  "components": {
    "schemas": {
      "CreateUserDto": {
        "type": "object",
        "properties": {
          "name": {
            "type": "string",
            "minLength": 2
          },
          "email": {
            "type": "string",
            "format": "email"
          }
        },
        "required": [
          "name",
          "email"
        ]
      }
    }
  }
}